odoo/addons/hr_employee_calendar_planning/README.rst
odoo/addons/hr_employee_calendar_planning/__init__.py
odoo/addons/hr_employee_calendar_planning/__manifest__.py
odoo/addons/hr_employee_calendar_planning/hooks.py
odoo/addons/hr_employee_calendar_planning/i18n/ca.po
odoo/addons/hr_employee_calendar_planning/i18n/ca_ES.po
odoo/addons/hr_employee_calendar_planning/i18n/es.po
odoo/addons/hr_employee_calendar_planning/i18n/hr_employee_calendar_planning.pot
odoo/addons/hr_employee_calendar_planning/i18n/it.po
odoo/addons/hr_employee_calendar_planning/migrations/12.0.1.1.0/post-migration.py
odoo/addons/hr_employee_calendar_planning/models/__init__.py
odoo/addons/hr_employee_calendar_planning/models/hr_employee.py
odoo/addons/hr_employee_calendar_planning/models/resource_calendar.py
odoo/addons/hr_employee_calendar_planning/readme/CONFIGURE.rst
odoo/addons/hr_employee_calendar_planning/readme/CONTRIBUTORS.rst
odoo/addons/hr_employee_calendar_planning/readme/DESCRIPTION.rst
odoo/addons/hr_employee_calendar_planning/readme/INSTALL.rst
odoo/addons/hr_employee_calendar_planning/readme/ROADMAP.rst
odoo/addons/hr_employee_calendar_planning/security/ir.model.access.csv
odoo/addons/hr_employee_calendar_planning/static/description/icon.png
odoo/addons/hr_employee_calendar_planning/static/description/index.html
odoo/addons/hr_employee_calendar_planning/tests/__init__.py
odoo/addons/hr_employee_calendar_planning/tests/test_hr_employee_calendar_planning.py
odoo/addons/hr_employee_calendar_planning/views/hr_employee_views.xml
odoo12_addon_hr_employee_calendar_planning-12.0.1.1.2.dist-info/METADATA
odoo12_addon_hr_employee_calendar_planning-12.0.1.1.2.dist-info/WHEEL
odoo12_addon_hr_employee_calendar_planning-12.0.1.1.2.dist-info/top_level.txt
odoo12_addon_hr_employee_calendar_planning-12.0.1.1.2.dist-info/RECORD
